LICENSE
MANIFEST.in
README.md
setup.py
django_phone_confirmation.egg-info/PKG-INFO
django_phone_confirmation.egg-info/SOURCES.txt
django_phone_confirmation.egg-info/dependency_links.txt
django_phone_confirmation.egg-info/pbr.json
django_phone_confirmation.egg-info/requires.txt
django_phone_confirmation.egg-info/top_level.txt
phone_confirmation/__init__.py
phone_confirmation/admin.py
phone_confirmation/apps.py
phone_confirmation/fields.py
phone_confirmation/models.py
phone_confirmation/serializers.py
phone_confirmation/signals.py
phone_confirmation/tests.py
phone_confirmation/urls.py
phone_confirmation/views.py
phone_confirmation/migrations/0001_initial.py
phone_confirmation/migrations/0002_auto_20180714_2103.py
phone_confirmation/migrations/__init__.py
phone_confirmation/templates/phone_confirmation/message.txt