Metadata-Version: 1.1
Name: django-phone-confirmation
Version: 0.3.6
Summary: A Django app to validate cell phone numbers through SMS messages and REST.
Home-page: https://github.com/ricardosasilva/django_phone_confirmation
Author: Ricardo S. A. Silva
Author-email: ricardo@salamandra.cc
License: MIT
Keywords: django cell phone confirmation
Platform: UNKNOWN
Classifier: Development Status :: 3 - Alpha
Classifier: Framework :: Django
Classifier: Intended Audience :: Developers
Classifier: License :: OSI Approved :: MIT License
Classifier: Operating System :: OS Independent
Classifier: Programming Language :: Python
Classifier: Programming Language :: Python :: 3
